DESCRIPTION.md
MANIFEST.in
setup.py
pyopenpgparse/__init__.py
pyopenpgparse/packets.py
pyopenpgparse/parser.py
pyopenpgparse/utils.py
pyopenpgparse.egg-info/PKG-INFO
pyopenpgparse.egg-info/SOURCES.txt
pyopenpgparse.egg-info/dependency_links.txt
pyopenpgparse.egg-info/requires.txt
pyopenpgparse.egg-info/top_level.txt
pyopenpgparse/tests/__init__.py
pyopenpgparse/tests/test_armor.py
pyopenpgparse/tests/test_packet.py